ziocryptor/__init__.py
ziocryptor/core.py
ziocryptor-10.3.0.dist-info/licenses/LICENSE.txt
ziocryptor-10.3.0.dist-info/METADATA
ziocryptor-10.3.0.dist-info/WHEEL
ziocryptor-10.3.0.dist-info/top_level.txt
ziocryptor-10.3.0.dist-info/RECORD
