Metadata-Version: 2.4
Name: ziocryptor
Version: 10.3.0
Summary: Hybrid AES + RSA Encryption Tool by Ziole Visa Charles
Author-email: Ziole Visa Charles <oozvc.co@gmail.com>
License-Expression: MIT
Project-URL: Homepage, https://github.com/oozvc/ziocryptor
Project-URL: Source, https://github.com/oozvc/ziocryptor
Project-URL: Issues, https://github.com/oozvc/ziocryptor/issues
Keywords: encryption,AES,RSA,security,ziocryptor,CLI,python
Classifier: Programming Language :: Python :: 3
Classifier: Operating System :: OS Independent
Classifier: Topic :: Security :: Cryptography
Requires-Python: >=3.8
License-File: LICENSE.txt
Dynamic: license-file
